{
	"community": "https://community.anytype.io/",
	"docs": "https://doc.anytype.io/",
	"telegram": "https://t.me/anytype",
	"twitter": "https://twitter.com/AnytypeLabs",
	"feedback": "https://community.anytype.io/composer",
	"survey": {
		"new": "https://anytype.typeform.com/to/GlS8NAKb",
		"pmf": "https://anytype.typeform.com/to/CXu6nG9R#anytypeid=%s",
		"exit": "https://anytype.typeform.com/to/lSyoRr8U"
	},
	"unsplash": {
		"site": "https://unsplash.com/",
		"utm": "?utm_source=Anytype&utm_medium=referral"
	},
	"protocol": "anytype://"
}
